[
  {
    "id": "f0beabd6-5382-45a5-98f5-847f30857acf",
    "data": [
      {
        "text": "Wasp sting",
        "userDefined": false
      }
    ],
    "isTemplate": false,
    "count": 0,
    "updated": 0
  },
  {
    "id": "5885c832-1895-4b78-a7a0-9bc59d89d312",
    "data": [
      {
        "text": "Wasp",
        "userDefined": false
      }
    ],
    "isTemplate": false,
    "count": 0,
    "updated": 0
  },
  {
    "id": "a0b1161d-035d-4d50-b055-13f3f3abcbff",
    "data": [
      {
        "text": "Bee",
        "userDefined": false
      }
    ],
    "isTemplate": false,
    "count": 0,
    "updated": 0
  },
  {
    "id": "3035fd93-cafd-49ac-b64b-4fa5db12cdbd",
    "data": [
      {
        "text": "What do you know about bee sting",
        "userDefined": false
      }
    ],
    "isTemplate": false,
    "count": 0,
    "updated": 0
  },
  {
    "id": "dc070cf2-99a9-4e8a-b627-043a02df64b2",
    "data": [
      {
        "text": "Bee sting",
        "userDefined": false
      }
    ],
    "isTemplate": false,
    "count": 0,
    "updated": 0
  }
]