[
  {
    "id": "0f23c27d-231b-425a-be4b-3366423109bf",
    "data": [
      {
        "text": "is that what you mean",
        "userDefined": false
      }
    ],
    "isTemplate": false,
    "count": 0,
    "updated": 0
  },
  {
    "id": "de98c6fb-0efa-4c5c-9ac6-126886e2540a",
    "data": [
      {
        "text": "what exactly do you mean",
        "userDefined": false
      }
    ],
    "isTemplate": false,
    "count": 1,
    "updated": 0
  },
  {
    "id": "1be123a2-7739-467f-8d72-c91e895b9cb1",
    "data": [
      {
        "text": "but what do you mean",
        "userDefined": false
      }
    ],
    "isTemplate": false,
    "count": 0,
    "updated": 0
  },
  {
    "id": "cb3a1ce8-826f-477d-a44b-d59b628a8d9c",
    "data": [
      {
        "text": "what do you mean exactly",
        "userDefined": false
      }
    ],
    "isTemplate": false,
    "count": 0,
    "updated": 0
  },
  {
    "id": "f35bbdea-0bc6-4955-8242-e54f6284a435",
    "data": [
      {
        "text": "what do you mean",
        "userDefined": false
      }
    ],
    "isTemplate": false,
    "count": 0,
    "updated": 0
  }
]